pyperfstats/__init__.py
pyperfstats/cli.py
pyperfstats/live_monitor.py
pyperfstats/profiler.py
pyperfstats/visualize.py
pyperfstats-0.1.1.dist-info/licenses/LICENSE
pyperfstats-0.1.1.dist-info/METADATA
pyperfstats-0.1.1.dist-info/WHEEL
pyperfstats-0.1.1.dist-info/entry_points.txt
pyperfstats-0.1.1.dist-info/top_level.txt
pyperfstats-0.1.1.dist-info/RECORD
