Metadata-Version: 2.4
Name: pyperfstats
Version: 0.1.1
Summary: A lightweight Python performance profiler
Home-page: https://github.com/Anish-Reddy-K/pyperfstats
Author: Anish Reddy
Author-email: Anish Reddy <anishreddy3456@gmail.com>
License: MIT
Project-URL: Homepage, https://github.com/Anish-Reddy-K/pyperfstats
Project-URL: Bug Tracker, https://github.com/Anish-Reddy-K/pyperfstats/issues
Classifier: Programming Language :: Python :: 3
Classifier: License :: OSI Approved :: MIT License
Classifier: Operating System :: OS Independent
Requires-Python: >=3.6
License-File: LICENSE
Requires-Dist: psutil>=5.8.0
Requires-Dist: matplotlib>=3.3.0
Requires-Dist: pandas>=1.2.0
Requires-Dist: click>=7.0
Dynamic: author
Dynamic: home-page
Dynamic: license-file
Dynamic: requires-python
